flask_does_huey/__init__.py
flask_does_huey-0.5.10.dist-info/LICENSE
flask_does_huey-0.5.10.dist-info/METADATA
flask_does_huey-0.5.10.dist-info/WHEEL
flask_does_huey-0.5.10.dist-info/top_level.txt
flask_does_huey-0.5.10.dist-info/RECORD
